{
    "VehiclesCountEst": 10000,
    "bbox_map": {
        "maxlat": 24.525846856349926,
        "maxlon": 54.50527388472162,
        "minlat": 24.391563843143523,
        "minlon": 54.30485116084661
    },
    "bbox_roads": {
        "maxlat": 24.514656605249392,
        "maxlon": 54.48857199106537,
        "minlat": 24.402754094244056,
        "minlon": 54.321553054502864
    },
    "links": {
        "0": {
            "dst": 1,
            "edits": "=Speed120,=4Lanes",
            "lanes": 4,
            "length": 1.1612244131457476,
            "org": 0,
            "speed": 120,
            "type": "LineString"
        },
        "1": {
            "dst": 0,
            "edits": "-u-turn  ,=Speed120,=4Lanes",
            "lanes": 4,
            "length": 1.1612244131457476,
            "org": 1,
            "speed": 120,
            "type": "LineString"
        },
        "2": {
            "dst": 0,
            "edits": "-u-turn  ,=Speed120,=4Lanes",
            "lanes": 4,
            "length": 0.6769675011423381,
            "org": 2,
            "speed": 120,
            "type": "LineString"
        },
        "3": {
            "dst": 2,
            "edits": "=Speed120,=4Lanes",
            "lanes": 4,
            "length": 0.6769675011423381,
            "org": 0,
            "speed": 120,
            "type": "LineString"
        },
        "4": {
            "dst": 0,
            "edits": "-u-turn  ,=Speed100,+link5",
            "lanes": 3,
            "length": 1.4984628725962417,
            "org": 3,
            "speed": 100,
            "type": "LineString"
        },
        "5": {
            "dst": 3,
            "edits": "-left    ,-u-turn  ,=Speed100",
            "lanes": 3,
            "length": 1.4984628725962417,
            "org": 0,
            "speed": 100,
            "type": "LineString"
        },
        "6": {
            "dst": 2,
            "edits": "=Speed60",
            "lanes": 3,
            "length": 0.5014450896509145,
            "org": 4,
            "speed": 60,
            "type": "LineString"
        },
        "7": {
            "dst": 4,
            "edits": "=Speed60",
            "lanes": 3,
            "length": 0.5014450896509145,
            "org": 2,
            "speed": 60,
            "type": "LineString"
        },
        "8": {
            "dst": 4,
            "edits": "=Speed60",
            "lanes": 3,
            "length": 0.5566744164885307,
            "org": 5,
            "speed": 60,
            "type": "LineString"
        },
        "9": {
            "dst": 5,
            "edits": "-left_T  ,=Speed60",
            "lanes": 3,
            "length": 0.5566744164885307,
            "org": 4,
            "speed": 60,
            "type": "LineString"
        },
        "10": {
            "dst": 2,
            "edits": "=Speed120,=4Lanes",
            "lanes": 4,
            "length": 0.8703066784499157,
            "org": 6,
            "speed": 120,
            "type": "LineString"
        },
        "11": {
            "dst": 6,
            "edits": "-left_T  ,=Speed120,=4Lanes",
            "lanes": 4,
            "length": 0.8703066784499157,
            "org": 2,
            "speed": 120,
            "type": "LineString"
        },
        "12": {
            "dst": 7,
            "edits": "=Speed100,=4Lanes",
            "lanes": 4,
            "length": 1.022670426110888,
            "org": 3,
            "speed": 100,
            "type": "LineString"
        },
        "13": {
            "dst": 3,
            "edits": "-left    ,-u-turn  ,=Speed100,=4Lanes",
            "lanes": 4,
            "length": 1.022670426110888,
            "org": 7,
            "speed": 100,
            "type": "LineString"
        },
        "14": {
            "dst": 3,
            "edits": "-left    ,-u-turn  ,=Speed100,=4Lanes",
            "lanes": 4,
            "length": 0.7068406896457419,
            "org": 5,
            "speed": 100,
            "type": "LineString"
        },
        "15": {
            "dst": 5,
            "edits": "-left_T  ,=Speed100,=4Lanes",
            "lanes": 4,
            "length": 0.7068406896457419,
            "org": 3,
            "speed": 100,
            "type": "LineString"
        },
        "16": {
            "dst": 8,
            "edits": "-left_T  ,=Speed100,=4Lanes",
            "lanes": 4,
            "length": 0.5871614487522837,
            "org": 5,
            "speed": 100,
            "type": "LineString"
        },
        "17": {
            "dst": 5,
            "edits": "-left_T  ,=Speed100,=4Lanes",
            "lanes": 4,
            "length": 0.5871614487522837,
            "org": 8,
            "speed": 100,
            "type": "LineString"
        },
        "18": {
            "dst": 3,
            "edits": "-left    ,-u-turn  ,=Speed100",
            "lanes": 3,
            "length": 0.82028158519834,
            "org": 9,
            "speed": 100,
            "type": "LineString"
        },
        "19": {
            "dst": 9,
            "edits": "-u-turn  ,=Speed100",
            "lanes": 3,
            "length": 0.82028158519834,
            "org": 3,
            "speed": 100,
            "type": "LineString"
        },
        "20": {
            "dst": 6,
            "edits": "-left_T  ,=Speed60",
            "lanes": 3,
            "length": 0.8125652081127364,
            "org": 8,
            "speed": 60,
            "type": "LineString"
        },
        "21": {
            "dst": 8,
            "edits": "-left_T  ,=Speed60",
            "lanes": 3,
            "length": 0.8125652081127364,
            "org": 6,
            "speed": 60,
            "type": "LineString"
        },
        "22": {
            "dst": 10,
            "edits": "=Speed120,=4Lanes",
            "lanes": 4,
            "length": 1.484834201144002,
            "org": 9,
            "speed": 120,
            "type": "LineString"
        },
        "23": {
            "dst": 9,
            "edits": "-left    ,-u-turn  ,=Speed120,=4Lanes",
            "lanes": 4,
            "length": 1.484834201144002,
            "org": 10,
            "speed": 120,
            "type": "LineString"
        },
        "24": {
            "dst": 11,
            "edits": "-u-turn  ,=Speed100,=4Lanes",
            "lanes": 4,
            "length": 1.4094898727594125,
            "org": 8,
            "speed": 100,
            "type": "LineString"
        },
        "25": {
            "dst": 8,
            "edits": "-left_T  ,=Speed100,=4Lanes",
            "lanes": 4,
            "length": 1.4094898727594125,
            "org": 11,
            "speed": 100,
            "type": "LineString"
        },
        "26": {
            "dst": 6,
            "edits": "-left_T  ,=Speed120,=4Lanes",
            "lanes": 4,
            "length": 2.0693642846355136,
            "org": 12,
            "speed": 120,
            "type": "LineString"
        },
        "27": {
            "dst": 12,
            "edits": "-u-turn  ,=Speed120,=4Lanes",
            "lanes": 4,
            "length": 2.0693642846355136,
            "org": 6,
            "speed": 120,
            "type": "LineString"
        },
        "28": {
            "dst": 13,
            "edits": "=Speed120,=4Lanes",
            "lanes": 4,
            "length": 2.420311388002477,
            "org": 9,
            "speed": 120,
            "type": "LineString"
        },
        "29": {
            "dst": 9,
            "edits": "-u-turn  ,=Speed120,=4Lanes",
            "lanes": 4,
            "length": 2.420311388002477,
            "org": 13,
            "speed": 120,
            "type": "LineString"
        },
        "30": {
            "dst": 14,
            "edits": "=Speed100,=4Lanes",
            "lanes": 4,
            "length": 0.9094978885913466,
            "org": 11,
            "speed": 100,
            "type": "LineString"
        },
        "31": {
            "dst": 11,
            "edits": "-u-turn  ,=Speed100,=4Lanes",
            "lanes": 4,
            "length": 0.9094978885913466,
            "org": 14,
            "speed": 100,
            "type": "LineString"
        },
        "32": {
            "dst": 12,
            "edits": "-u-turn",
            "lanes": 3,
            "length": 0.6155845130769513,
            "org": 15,
            "speed": 80,
            "type": "LineString"
        },
        "33": {
            "dst": 15,
            "edits": "",
            "lanes": 3,
            "length": 0.6155845130769513,
            "org": 12,
            "speed": 80,
            "type": "LineString"
        },
        "34": {
            "dst": 14,
            "edits": "",
            "lanes": 3,
            "length": 0.6021388755616787,
            "org": 15,
            "speed": 80,
            "type": "LineString"
        },
        "35": {
            "dst": 15,
            "edits": "",
            "lanes": 3,
            "length": 0.6021388755616787,
            "org": 14,
            "speed": 80,
            "type": "LineString"
        },
        "36": {
            "dst": 16,
            "edits": "-left_T  ,=Speed100,=4Lanes",
            "lanes": 4,
            "length": 0.7690887087778161,
            "org": 14,
            "speed": 100,
            "type": "LineString"
        },
        "37": {
            "dst": 14,
            "edits": "=Speed100,=4Lanes",
            "lanes": 4,
            "length": 0.7690887087778161,
            "org": 16,
            "speed": 100,
            "type": "LineString"
        },
        "38": {
            "dst": 14,
            "edits": "=Speed100,=4Lanes",
            "lanes": 4,
            "length": 0.9875788060370854,
            "org": 17,
            "speed": 100,
            "type": "LineString"
        },
        "39": {
            "dst": 17,
            "edits": "=Speed100,=4Lanes",
            "lanes": 4,
            "length": 0.9875788060370854,
            "org": 14,
            "speed": 100,
            "type": "LineString"
        },
        "40": {
            "dst": 12,
            "edits": "-u-turn  ,=Speed120,=4Lanes",
            "lanes": 4,
            "length": 1.6676272606772458,
            "org": 18,
            "speed": 120,
            "type": "LineString"
        },
        "41": {
            "dst": 18,
            "edits": "-left_T  ,=Speed120,=4Lanes",
            "lanes": 4,
            "length": 1.6676272606772458,
            "org": 12,
            "speed": 120,
            "type": "LineString"
        },
        "42": {
            "dst": 15,
            "edits": "",
            "lanes": 3,
            "length": 1.6660426670601862,
            "org": 19,
            "speed": 80,
            "type": "LineString"
        },
        "43": {
            "dst": 19,
            "edits": "-left_T",
            "lanes": 3,
            "length": 1.6660426670601862,
            "org": 15,
            "speed": 80,
            "type": "LineString"
        },
        "44": {
            "dst": 17,
            "edits": "",
            "lanes": 3,
            "length": 0.6256025087551278,
            "org": 16,
            "speed": 80,
            "type": "LineString"
        },
        "45": {
            "dst": 16,
            "edits": "-left_T",
            "lanes": 3,
            "length": 0.6256025087551278,
            "org": 17,
            "speed": 80,
            "type": "LineString"
        },
        "46": {
            "dst": 20,
            "edits": "=Speed120,=4Lanes",
            "lanes": 4,
            "length": 1.6092620230488097,
            "org": 13,
            "speed": 120,
            "type": "LineString"
        },
        "47": {
            "dst": 13,
            "edits": "=Speed120,=4Lanes",
            "lanes": 4,
            "length": 1.6092620230488097,
            "org": 20,
            "speed": 120,
            "type": "LineString"
        },
        "48": {
            "dst": 16,
            "edits": "-left_T  ,=Speed100,=4Lanes",
            "lanes": 4,
            "length": 0.8588725529152427,
            "org": 21,
            "speed": 100,
            "type": "LineString"
        },
        "49": {
            "dst": 21,
            "edits": "=Speed100,=4Lanes",
            "lanes": 4,
            "length": 0.8588725529152427,
            "org": 16,
            "speed": 100,
            "type": "LineString"
        },
        "50": {
            "dst": 17,
            "edits": "",
            "lanes": 3,
            "length": 1.2758372340046462,
            "org": 20,
            "speed": 80,
            "type": "LineString"
        },
        "51": {
            "dst": 20,
            "edits": "",
            "lanes": 3,
            "length": 1.2758372340046462,
            "org": 17,
            "speed": 80,
            "type": "LineString"
        },
        "52": {
            "dst": 22,
            "edits": "=Speed100,=4Lanes",
            "lanes": 4,
            "length": 0.858834685732421,
            "org": 17,
            "speed": 100,
            "type": "LineString"
        },
        "53": {
            "dst": 17,
            "edits": "=Speed100,=4Lanes",
            "lanes": 4,
            "length": 0.858834685732421,
            "org": 22,
            "speed": 100,
            "type": "LineString"
        },
        "54": {
            "dst": 18,
            "edits": "-left_T",
            "lanes": 3,
            "length": 0.3575437886629683,
            "org": 19,
            "speed": 80,
            "type": "LineString"
        },
        "55": {
            "dst": 19,
            "edits": "-left_T",
            "lanes": 3,
            "length": 0.3575437886629683,
            "org": 18,
            "speed": 80,
            "type": "LineString"
        },
        "56": {
            "dst": 19,
            "edits": "-left_T",
            "lanes": 3,
            "length": 0.617382505608806,
            "org": 21,
            "speed": 80,
            "type": "LineString"
        },
        "57": {
            "dst": 21,
            "edits": "",
            "lanes": 3,
            "length": 0.617382505608806,
            "org": 19,
            "speed": 80,
            "type": "LineString"
        },
        "58": {
            "dst": 21,
            "edits": "",
            "lanes": 3,
            "length": 0.6255965084402257,
            "org": 22,
            "speed": 80,
            "type": "LineString"
        },
        "59": {
            "dst": 22,
            "edits": "",
            "lanes": 3,
            "length": 0.6255965084402257,
            "org": 21,
            "speed": 80,
            "type": "LineString"
        },
        "60": {
            "dst": 18,
            "edits": "-left_T  ,=Speed120,=4Lanes",
            "lanes": 4,
            "length": 1.1185264331346632,
            "org": 23,
            "speed": 120,
            "type": "LineString"
        },
        "61": {
            "dst": 23,
            "edits": "-u-turn  ,=Speed120,=4Lanes",
            "lanes": 4,
            "length": 1.1185264331346632,
            "org": 18,
            "speed": 120,
            "type": "LineString"
        },
        "62": {
            "dst": 20,
            "edits": "=Speed120,=4Lanes",
            "lanes": 4,
            "length": 0.874204010084204,
            "org": 24,
            "speed": 120,
            "type": "LineString"
        },
        "63": {
            "dst": 24,
            "edits": "-left_T  ,=Speed120,=4Lanes",
            "lanes": 4,
            "length": 0.874204010084204,
            "org": 20,
            "speed": 120,
            "type": "LineString"
        },
        "64": {
            "dst": 24,
            "edits": "-left_T",
            "lanes": 3,
            "length": 1.2017242655792402,
            "org": 22,
            "speed": 80,
            "type": "LineString"
        },
        "65": {
            "dst": 22,
            "edits": "",
            "lanes": 3,
            "length": 1.2017242655792402,
            "org": 24,
            "speed": 80,
            "type": "LineString"
        },
        "66": {
            "dst": 21,
            "edits": "=Speed100,=4Lanes",
            "lanes": 4,
            "length": 0.982795603500593,
            "org": 25,
            "speed": 100,
            "type": "LineString"
        },
        "67": {
            "dst": 25,
            "edits": "=Speed100,=4Lanes",
            "lanes": 4,
            "length": 0.982795603500593,
            "org": 21,
            "speed": 100,
            "type": "LineString"
        },
        "68": {
            "dst": 22,
            "edits": "=Speed100,=4Lanes",
            "lanes": 4,
            "length": 0.883066694423697,
            "org": 26,
            "speed": 100,
            "type": "LineString"
        },
        "69": {
            "dst": 26,
            "edits": "=Speed100,=4Lanes",
            "lanes": 4,
            "length": 0.883066694423697,
            "org": 22,
            "speed": 100,
            "type": "LineString"
        },
        "70": {
            "dst": 23,
            "edits": "-u-turn",
            "lanes": 3,
            "length": 0.8900358769522203,
            "org": 25,
            "speed": 80,
            "type": "LineString"
        },
        "71": {
            "dst": 25,
            "edits": "",
            "lanes": 3,
            "length": 0.8900358769522203,
            "org": 23,
            "speed": 80,
            "type": "LineString"
        },
        "72": {
            "dst": 25,
            "edits": "",
            "lanes": 3,
            "length": 0.6166849277756826,
            "org": 26,
            "speed": 80,
            "type": "LineString"
        },
        "73": {
            "dst": 26,
            "edits": "",
            "lanes": 3,
            "length": 0.6166849277756826,
            "org": 25,
            "speed": 80,
            "type": "LineString"
        },
        "74": {
            "dst": 24,
            "edits": "-left_T  ,=Speed120,=4Lanes",
            "lanes": 4,
            "length": 1.244666205474401,
            "org": 27,
            "speed": 120,
            "type": "LineString"
        },
        "75": {
            "dst": 27,
            "edits": "-left_T  ,=Speed120,=4Lanes",
            "lanes": 4,
            "length": 1.244666205474401,
            "org": 24,
            "speed": 120,
            "type": "LineString"
        },
        "76": {
            "dst": 25,
            "edits": "=Speed100,=4Lanes",
            "lanes": 4,
            "length": 0.6422975612224165,
            "org": 28,
            "speed": 100,
            "type": "LineString"
        },
        "77": {
            "dst": 28,
            "edits": "=Speed100,=4Lanes",
            "lanes": 4,
            "length": 0.6422975612224165,
            "org": 25,
            "speed": 100,
            "type": "LineString"
        },
        "78": {
            "dst": 23,
            "edits": "-u-turn  ,=Speed120,=4Lanes",
            "lanes": 4,
            "length": 0.7426673562236954,
            "org": 29,
            "speed": 120,
            "type": "LineString"
        },
        "79": {
            "dst": 29,
            "edits": "-left_T  ,=Speed120,=4Lanes",
            "lanes": 4,
            "length": 0.7426673562236954,
            "org": 23,
            "speed": 120,
            "type": "LineString"
        },
        "80": {
            "dst": 30,
            "edits": "=Speed100,=4Lanes",
            "lanes": 4,
            "length": 0.5787151345571404,
            "org": 26,
            "speed": 100,
            "type": "LineString"
        },
        "81": {
            "dst": 26,
            "edits": "=Speed100,=4Lanes",
            "lanes": 4,
            "length": 0.5787151345571404,
            "org": 30,
            "speed": 100,
            "type": "LineString"
        },
        "82": {
            "dst": 28,
            "edits": "",
            "lanes": 3,
            "length": 0.6068650541852622,
            "org": 30,
            "speed": 80,
            "type": "LineString"
        },
        "83": {
            "dst": 30,
            "edits": "",
            "lanes": 3,
            "length": 0.6068650541852622,
            "org": 28,
            "speed": 80,
            "type": "LineString"
        },
        "84": {
            "dst": 29,
            "edits": "-left_T",
            "lanes": 3,
            "length": 0.9868216134126261,
            "org": 28,
            "speed": 80,
            "type": "LineString"
        },
        "85": {
            "dst": 28,
            "edits": "",
            "lanes": 3,
            "length": 0.9868216134126261,
            "org": 29,
            "speed": 80,
            "type": "LineString"
        },
        "86": {
            "dst": 30,
            "edits": "",
            "lanes": 3,
            "length": 0.8201619738125726,
            "org": 27,
            "speed": 80,
            "type": "LineString"
        },
        "87": {
            "dst": 27,
            "edits": "-left_T",
            "lanes": 3,
            "length": 0.8201619738125726,
            "org": 30,
            "speed": 80,
            "type": "LineString"
        },
        "88": {
            "dst": 28,
            "edits": "=Speed100,=4Lanes",
            "lanes": 4,
            "length": 1.0085994604774748,
            "org": 31,
            "speed": 100,
            "type": "LineString"
        },
        "89": {
            "dst": 31,
            "edits": "=Speed100,=4Lanes",
            "lanes": 4,
            "length": 1.0085994604774748,
            "org": 28,
            "speed": 100,
            "type": "LineString"
        },
        "90": {
            "dst": 32,
            "edits": "=Speed100,=4Lanes",
            "lanes": 4,
            "length": 1.0253640151580086,
            "org": 30,
            "speed": 100,
            "type": "LineString"
        },
        "91": {
            "dst": 30,
            "edits": "=Speed100,=4Lanes",
            "lanes": 4,
            "length": 1.0253640151580086,
            "org": 32,
            "speed": 100,
            "type": "LineString"
        },
        "92": {
            "dst": 33,
            "edits": "-left_T  ,=Speed120,=4Lanes",
            "lanes": 4,
            "length": 1.0007871139178455,
            "org": 29,
            "speed": 120,
            "type": "LineString"
        },
        "93": {
            "dst": 29,
            "edits": "-left_T  ,=Speed120,=4Lanes",
            "lanes": 4,
            "length": 1.0007871139178455,
            "org": 33,
            "speed": 120,
            "type": "LineString"
        },
        "94": {
            "dst": 27,
            "edits": "-left_T  ,=Speed120,=4Lanes",
            "lanes": 4,
            "length": 1.0170664213626617,
            "org": 34,
            "speed": 120,
            "type": "LineString"
        },
        "95": {
            "dst": 34,
            "edits": "-left_T  ,=Speed120,=4Lanes",
            "lanes": 4,
            "length": 1.0170664213626617,
            "org": 27,
            "speed": 120,
            "type": "LineString"
        },
        "96": {
            "dst": 33,
            "edits": "-left_T",
            "lanes": 3,
            "length": 1.1012779625494376,
            "org": 31,
            "speed": 80,
            "type": "LineString"
        },
        "97": {
            "dst": 31,
            "edits": "",
            "lanes": 3,
            "length": 1.1012779625494376,
            "org": 33,
            "speed": 80,
            "type": "LineString"
        },
        "98": {
            "dst": 31,
            "edits": "",
            "lanes": 3,
            "length": 0.6256087034976496,
            "org": 32,
            "speed": 80,
            "type": "LineString"
        },
        "99": {
            "dst": 32,
            "edits": "",
            "lanes": 3,
            "length": 0.6256087034976496,
            "org": 31,
            "speed": 80,
            "type": "LineString"
        },
        "100": {
            "dst": 32,
            "edits": "",
            "lanes": 3,
            "length": 0.7806555879395364,
            "org": 34,
            "speed": 80,
            "type": "LineString"
        },
        "101": {
            "dst": 34,
            "edits": "-left_T",
            "lanes": 3,
            "length": 0.7806555879395364,
            "org": 32,
            "speed": 80,
            "type": "LineString"
        },
        "102": {
            "dst": 32,
            "edits": "=Speed100,=4Lanes",
            "lanes": 4,
            "length": 0.3566923943691136,
            "org": 35,
            "speed": 100,
            "type": "LineString"
        },
        "103": {
            "dst": 35,
            "edits": "=Speed100,=4Lanes",
            "lanes": 4,
            "length": 0.3566923943691136,
            "org": 32,
            "speed": 100,
            "type": "LineString"
        },
        "104": {
            "dst": 31,
            "edits": "=Speed100,=4Lanes",
            "lanes": 4,
            "length": 0.645241481811926,
            "org": 36,
            "speed": 100,
            "type": "LineString"
        },
        "105": {
            "dst": 36,
            "edits": "=Speed100,=4Lanes",
            "lanes": 4,
            "length": 0.645241481811926,
            "org": 31,
            "speed": 100,
            "type": "LineString"
        },
        "106": {
            "dst": 36,
            "edits": "",
            "lanes": 3,
            "length": 0.6181693978278685,
            "org": 35,
            "speed": 80,
            "type": "LineString"
        },
        "107": {
            "dst": 35,
            "edits": "",
            "lanes": 3,
            "length": 0.6181693978278685,
            "org": 36,
            "speed": 80,
            "type": "LineString"
        },
        "108": {
            "dst": 35,
            "edits": "=Speed100,=4Lanes",
            "lanes": 4,
            "length": 0.34303851525346185,
            "org": 37,
            "speed": 100,
            "type": "LineString"
        },
        "109": {
            "dst": 37,
            "edits": "=Speed100,=4Lanes",
            "lanes": 4,
            "length": 0.34303851525346185,
            "org": 35,
            "speed": 100,
            "type": "LineString"
        },
        "110": {
            "dst": 34,
            "edits": "-left_T  ,=Speed120,=4Lanes",
            "lanes": 4,
            "length": 1.1041794902724928,
            "org": 38,
            "speed": 120,
            "type": "LineString"
        },
        "111": {
            "dst": 38,
            "edits": "=Speed120,=4Lanes",
            "lanes": 4,
            "length": 1.1041794902724928,
            "org": 34,
            "speed": 120,
            "type": "LineString"
        },
        "112": {
            "dst": 36,
            "edits": "=Speed100,=4Lanes",
            "lanes": 4,
            "length": 0.33187731798613623,
            "org": 39,
            "speed": 100,
            "type": "LineString"
        },
        "113": {
            "dst": 39,
            "edits": "=Speed100,=4Lanes",
            "lanes": 4,
            "length": 0.33187731798613623,
            "org": 36,
            "speed": 100,
            "type": "LineString"
        },
        "114": {
            "dst": 39,
            "edits": "",
            "lanes": 3,
            "length": 0.6174461580436114,
            "org": 37,
            "speed": 80,
            "type": "LineString"
        },
        "115": {
            "dst": 37,
            "edits": "",
            "lanes": 3,
            "length": 0.6174461580436114,
            "org": 39,
            "speed": 80,
            "type": "LineString"
        },
        "116": {
            "dst": 40,
            "edits": "-u-turn  ,=Speed120,=4Lanes",
            "lanes": 4,
            "length": 1.7474097732753797,
            "org": 33,
            "speed": 120,
            "type": "LineString"
        },
        "117": {
            "dst": 33,
            "edits": "-left_T  ,=Speed120,=4Lanes",
            "lanes": 4,
            "length": 1.7474097732753797,
            "org": 40,
            "speed": 120,
            "type": "LineString"
        },
        "118": {
            "dst": 37,
            "edits": "=Speed100,=4Lanes",
            "lanes": 4,
            "length": 0.7517718310458976,
            "org": 41,
            "speed": 100,
            "type": "LineString"
        },
        "119": {
            "dst": 41,
            "edits": "=Speed100,=4Lanes",
            "lanes": 4,
            "length": 0.7517718310458976,
            "org": 37,
            "speed": 100,
            "type": "LineString"
        },
        "120": {
            "dst": 39,
            "edits": "=Speed100,=4Lanes",
            "lanes": 4,
            "length": 0.7464683943674684,
            "org": 42,
            "speed": 100,
            "type": "LineString"
        },
        "121": {
            "dst": 42,
            "edits": "=Speed100,=4Lanes",
            "lanes": 4,
            "length": 0.7464683943674684,
            "org": 39,
            "speed": 100,
            "type": "LineString"
        },
        "122": {
            "dst": 41,
            "edits": "",
            "lanes": 3,
            "length": 0.832173678669232,
            "org": 38,
            "speed": 80,
            "type": "LineString"
        },
        "123": {
            "dst": 38,
            "edits": "",
            "lanes": 3,
            "length": 0.832173678669232,
            "org": 41,
            "speed": 80,
            "type": "LineString"
        },
        "124": {
            "dst": 42,
            "edits": "",
            "lanes": 3,
            "length": 0.6115430814442673,
            "org": 41,
            "speed": 80,
            "type": "LineString"
        },
        "125": {
            "dst": 41,
            "edits": "",
            "lanes": 3,
            "length": 0.6115430814442673,
            "org": 42,
            "speed": 80,
            "type": "LineString"
        },
        "126": {
            "dst": 43,
            "edits": "",
            "lanes": 3,
            "length": 0.6637324962841514,
            "org": 42,
            "speed": 80,
            "type": "LineString"
        },
        "127": {
            "dst": 42,
            "edits": "",
            "lanes": 3,
            "length": 0.6637324962841514,
            "org": 43,
            "speed": 80,
            "type": "LineString"
        },
        "128": {
            "dst": 44,
            "edits": "",
            "lanes": 3,
            "length": 0.6994654880550836,
            "org": 40,
            "speed": 80,
            "type": "LineString"
        },
        "129": {
            "dst": 40,
            "edits": "-u-turn  ,-link117",
            "lanes": 3,
            "length": 0.6994654880550836,
            "org": 44,
            "speed": 80,
            "type": "LineString"
        },
        "130": {
            "dst": 44,
            "edits": "",
            "lanes": 3,
            "length": 1.0611354244161018,
            "org": 43,
            "speed": 80,
            "type": "LineString"
        },
        "131": {
            "dst": 43,
            "edits": "",
            "lanes": 3,
            "length": 1.0611354244161018,
            "org": 44,
            "speed": 80,
            "type": "LineString"
        },
        "132": {
            "dst": 45,
            "edits": "=Speed100,=4Lanes",
            "lanes": 4,
            "length": 0.7747889121483761,
            "org": 40,
            "speed": 100,
            "type": "LineString"
        },
        "133": {
            "dst": 40,
            "edits": "-u-turn  ,=Speed100,=4Lanes  ,-link128",
            "lanes": 4,
            "length": 0.7747889121483761,
            "org": 45,
            "speed": 100,
            "type": "LineString"
        },
        "134": {
            "dst": 41,
            "edits": "=Speed100,=4Lanes",
            "lanes": 4,
            "length": 1.5791918661803273,
            "org": 46,
            "speed": 100,
            "type": "LineString"
        },
        "135": {
            "dst": 46,
            "edits": "=Speed100,=4Lanes",
            "lanes": 4,
            "length": 1.5791918661803273,
            "org": 41,
            "speed": 100,
            "type": "LineString"
        },
        "136": {
            "dst": 47,
            "edits": "=Speed120,=4Lanes",
            "lanes": 4,
            "length": 2.3418237645127715,
            "org": 38,
            "speed": 120,
            "type": "LineString"
        },
        "137": {
            "dst": 38,
            "edits": "=Speed120,=4Lanes",
            "lanes": 4,
            "length": 2.3418237645127715,
            "org": 47,
            "speed": 120,
            "type": "LineString"
        },
        "138": {
            "dst": 42,
            "edits": "=4Lanes",
            "lanes": 4,
            "length": 1.586163552781936,
            "org": 48,
            "speed": 80,
            "type": "LineString"
        },
        "139": {
            "dst": 48,
            "edits": "=4Lanes",
            "lanes": 4,
            "length": 1.586163552781936,
            "org": 42,
            "speed": 80,
            "type": "LineString"
        },
        "140": {
            "dst": 45,
            "edits": "",
            "lanes": 3,
            "length": 0.4092169914302824,
            "org": 44,
            "speed": 80,
            "type": "LineString"
        },
        "141": {
            "dst": 44,
            "edits": "",
            "lanes": 3,
            "length": 0.4092169914302824,
            "org": 45,
            "speed": 80,
            "type": "LineString"
        },
        "142": {
            "dst": 43,
            "edits": "",
            "lanes": 3,
            "length": 1.573288800241077,
            "org": 49,
            "speed": 80,
            "type": "LineString"
        },
        "143": {
            "dst": 49,
            "edits": "",
            "lanes": 3,
            "length": 1.573288800241077,
            "org": 43,
            "speed": 80,
            "type": "LineString"
        },
        "144": {
            "dst": 50,
            "edits": "",
            "lanes": 3,
            "length": 0.4172087399081321,
            "org": 45,
            "speed": 80,
            "type": "LineString"
        },
        "145": {
            "dst": 45,
            "edits": "",
            "lanes": 3,
            "length": 0.4172087399081321,
            "org": 50,
            "speed": 80,
            "type": "LineString"
        },
        "146": {
            "dst": 48,
            "edits": "",
            "lanes": 3,
            "length": 0.5949866958307629,
            "org": 46,
            "speed": 80,
            "type": "LineString"
        },
        "147": {
            "dst": 46,
            "edits": "",
            "lanes": 3,
            "length": 0.5949866958307629,
            "org": 48,
            "speed": 80,
            "type": "LineString"
        },
        "148": {
            "dst": 49,
            "edits": "",
            "lanes": 3,
            "length": 0.6851906975622202,
            "org": 48,
            "speed": 80,
            "type": "LineString"
        },
        "149": {
            "dst": 48,
            "edits": "",
            "lanes": 3,
            "length": 0.6851906975622202,
            "org": 49,
            "speed": 80,
            "type": "LineString"
        },
        "150": {
            "dst": 45,
            "edits": "=Speed100",
            "lanes": 3,
            "length": 1.6009715640420583,
            "org": 51,
            "speed": 100,
            "type": "LineString"
        },
        "151": {
            "dst": 51,
            "edits": "=Speed100",
            "lanes": 3,
            "length": 1.6009715640420583,
            "org": 45,
            "speed": 100,
            "type": "LineString"
        },
        "152": {
            "dst": 46,
            "edits": "=Speed100,=4Lanes",
            "lanes": 4,
            "length": 0.7711847925451072,
            "org": 52,
            "speed": 100,
            "type": "LineString"
        },
        "153": {
            "dst": 52,
            "edits": "=Speed100,=4Lanes",
            "lanes": 4,
            "length": 0.7711847925451072,
            "org": 46,
            "speed": 100,
            "type": "LineString"
        },
        "154": {
            "dst": 53,
            "edits": "",
            "lanes": 3,
            "length": 0.6413611274937121,
            "org": 49,
            "speed": 80,
            "type": "LineString"
        },
        "155": {
            "dst": 49,
            "edits": "",
            "lanes": 3,
            "length": 0.6413611274937121,
            "org": 53,
            "speed": 80,
            "type": "LineString"
        },
        "156": {
            "dst": 54,
            "edits": "",
            "lanes": 3,
            "length": 1.577916087352281,
            "org": 50,
            "speed": 80,
            "type": "LineString"
        },
        "157": {
            "dst": 50,
            "edits": "",
            "lanes": 3,
            "length": 1.577916087352281,
            "org": 54,
            "speed": 80,
            "type": "LineString"
        },
        "158": {
            "dst": 48,
            "edits": "=4Lanes",
            "lanes": 4,
            "length": 0.7753899382775173,
            "org": 55,
            "speed": 80,
            "type": "LineString"
        },
        "159": {
            "dst": 55,
            "edits": "=4Lanes",
            "lanes": 4,
            "length": 0.7753899382775173,
            "org": 48,
            "speed": 80,
            "type": "LineString"
        },
        "160": {
            "dst": 52,
            "edits": "",
            "lanes": 3,
            "length": 1.2240334949485656,
            "org": 47,
            "speed": 80,
            "type": "LineString"
        },
        "161": {
            "dst": 47,
            "edits": "",
            "lanes": 3,
            "length": 1.2240334949485656,
            "org": 52,
            "speed": 80,
            "type": "LineString"
        },
        "162": {
            "dst": 49,
            "edits": "",
            "lanes": 3,
            "length": 0.7600740693479213,
            "org": 56,
            "speed": 80,
            "type": "LineString"
        },
        "163": {
            "dst": 56,
            "edits": "",
            "lanes": 3,
            "length": 0.7600740693479213,
            "org": 49,
            "speed": 80,
            "type": "LineString"
        },
        "164": {
            "dst": 52,
            "edits": "",
            "lanes": 3,
            "length": 0.6120806884814569,
            "org": 55,
            "speed": 80,
            "type": "LineString"
        },
        "165": {
            "dst": 55,
            "edits": "",
            "lanes": 3,
            "length": 0.6120806884814569,
            "org": 52,
            "speed": 80,
            "type": "LineString"
        },
        "166": {
            "dst": 51,
            "edits": "",
            "lanes": 3,
            "length": 0.8360137480512578,
            "org": 53,
            "speed": 80,
            "type": "LineString"
        },
        "167": {
            "dst": 53,
            "edits": "",
            "lanes": 3,
            "length": 0.8360137480512578,
            "org": 51,
            "speed": 80,
            "type": "LineString"
        },
        "168": {
            "dst": 57,
            "edits": "=4Lanes",
            "lanes": 4,
            "length": 0.9055936550364506,
            "org": 47,
            "speed": 80,
            "type": "LineString"
        },
        "169": {
            "dst": 47,
            "edits": "=4Lanes",
            "lanes": 4,
            "length": 0.9055936550364506,
            "org": 57,
            "speed": 80,
            "type": "LineString"
        },
        "170": {
            "dst": 55,
            "edits": "",
            "lanes": 3,
            "length": 0.6674699344356322,
            "org": 56,
            "speed": 80,
            "type": "LineString"
        },
        "171": {
            "dst": 56,
            "edits": "",
            "lanes": 3,
            "length": 0.6674699344356322,
            "org": 55,
            "speed": 80,
            "type": "LineString"
        },
        "172": {
            "dst": 53,
            "edits": "",
            "lanes": 3,
            "length": 0.7712541917028858,
            "org": 58,
            "speed": 80,
            "type": "LineString"
        },
        "173": {
            "dst": 58,
            "edits": "",
            "lanes": 3,
            "length": 0.7712541917028858,
            "org": 53,
            "speed": 80,
            "type": "LineString"
        },
        "174": {
            "dst": 54,
            "edits": "",
            "lanes": 3,
            "length": 0.42655575649552857,
            "org": 51,
            "speed": 80,
            "type": "LineString"
        },
        "175": {
            "dst": 51,
            "edits": "",
            "lanes": 3,
            "length": 0.42655575649552857,
            "org": 54,
            "speed": 80,
            "type": "LineString"
        },
        "176": {
            "dst": 56,
            "edits": "",
            "lanes": 3,
            "length": 0.6424105789318045,
            "org": 58,
            "speed": 80,
            "type": "LineString"
        },
        "177": {
            "dst": 58,
            "edits": "",
            "lanes": 3,
            "length": 0.6424105789318045,
            "org": 56,
            "speed": 80,
            "type": "LineString"
        },
        "178": {
            "dst": 52,
            "edits": "=Speed100,=4Lanes",
            "lanes": 4,
            "length": 1.0228751781753265,
            "org": 59,
            "speed": 100,
            "type": "LineString"
        },
        "179": {
            "dst": 59,
            "edits": "=Speed100,=4Lanes",
            "lanes": 4,
            "length": 1.0228751781753265,
            "org": 52,
            "speed": 100,
            "type": "LineString"
        },
        "180": {
            "dst": 60,
            "edits": "=Speed100",
            "lanes": 3,
            "length": 0.763549635052659,
            "org": 51,
            "speed": 100,
            "type": "LineString"
        },
        "181": {
            "dst": 51,
            "edits": "=Speed100",
            "lanes": 3,
            "length": 0.763549635052659,
            "org": 60,
            "speed": 100,
            "type": "LineString"
        },
        "182": {
            "dst": 55,
            "edits": "=4Lanes",
            "lanes": 4,
            "length": 1.0273467747762972,
            "org": 61,
            "speed": 80,
            "type": "LineString"
        },
        "183": {
            "dst": 61,
            "edits": "=4Lanes",
            "lanes": 4,
            "length": 1.0273467747762972,
            "org": 55,
            "speed": 80,
            "type": "LineString"
        },
        "184": {
            "dst": 62,
            "edits": "",
            "lanes": 3,
            "length": 0.5918249878095343,
            "org": 57,
            "speed": 80,
            "type": "LineString"
        },
        "185": {
            "dst": 57,
            "edits": "-link231",
            "lanes": 3,
            "length": 0.5918249878095343,
            "org": 62,
            "speed": 80,
            "type": "LineString"
        },
        "186": {
            "dst": 60,
            "edits": "",
            "lanes": 3,
            "length": 0.863734864878113,
            "org": 58,
            "speed": 80,
            "type": "LineString"
        },
        "187": {
            "dst": 58,
            "edits": "",
            "lanes": 3,
            "length": 0.863734864878113,
            "org": 60,
            "speed": 80,
            "type": "LineString"
        },
        "188": {
            "dst": 54,
            "edits": "",
            "lanes": 3,
            "length": 0.7695071923272377,
            "org": 63,
            "speed": 80,
            "type": "LineString"
        },
        "189": {
            "dst": 63,
            "edits": "",
            "lanes": 3,
            "length": 0.7695071923272377,
            "org": 54,
            "speed": 80,
            "type": "LineString"
        },
        "190": {
            "dst": 56,
            "edits": "",
            "lanes": 3,
            "length": 1.0155746629702844,
            "org": 64,
            "speed": 80,
            "type": "LineString"
        },
        "191": {
            "dst": 64,
            "edits": "",
            "lanes": 3,
            "length": 1.0155746629702844,
            "org": 56,
            "speed": 80,
            "type": "LineString"
        },
        "192": {
            "dst": 59,
            "edits": "=Speed60",
            "lanes": 3,
            "length": 0.7722515946280784,
            "org": 62,
            "speed": 60,
            "type": "LineString"
        },
        "193": {
            "dst": 62,
            "edits": "=Speed60",
            "lanes": 3,
            "length": 0.7722515946280784,
            "org": 59,
            "speed": 60,
            "type": "LineString"
        },
        "194": {
            "dst": 57,
            "edits": "=4Lanes  ,-link231",
            "lanes": 4,
            "length": 0.9065156564358299,
            "org": 65,
            "speed": 80,
            "type": "LineString"
        },
        "195": {
            "dst": 65,
            "edits": "=4Lanes",
            "lanes": 4,
            "length": 0.9065156564358299,
            "org": 57,
            "speed": 80,
            "type": "LineString"
        },
        "196": {
            "dst": 58,
            "edits": "",
            "lanes": 3,
            "length": 0.9260610546425485,
            "org": 66,
            "speed": 80,
            "type": "LineString"
        },
        "197": {
            "dst": 66,
            "edits": "",
            "lanes": 3,
            "length": 0.9260610546425485,
            "org": 58,
            "speed": 80,
            "type": "LineString"
        },
        "198": {
            "dst": 60,
            "edits": "",
            "lanes": 3,
            "length": 0.42127721129857865,
            "org": 63,
            "speed": 80,
            "type": "LineString"
        },
        "199": {
            "dst": 63,
            "edits": "",
            "lanes": 3,
            "length": 0.42127721129857865,
            "org": 60,
            "speed": 80,
            "type": "LineString"
        },
        "200": {
            "dst": 61,
            "edits": "",
            "lanes": 3,
            "length": 0.6291983681256798,
            "org": 59,
            "speed": 80,
            "type": "LineString"
        },
        "201": {
            "dst": 59,
            "edits": "",
            "lanes": 3,
            "length": 0.6291983681256798,
            "org": 61,
            "speed": 80,
            "type": "LineString"
        },
        "202": {
            "dst": 62,
            "edits": "=Speed60",
            "lanes": 3,
            "length": 0.8022128629296261,
            "org": 67,
            "speed": 60,
            "type": "LineString"
        },
        "203": {
            "dst": 67,
            "edits": "=Speed60",
            "lanes": 3,
            "length": 0.8022128629296261,
            "org": 62,
            "speed": 60,
            "type": "LineString"
        },
        "204": {
            "dst": 64,
            "edits": "",
            "lanes": 3,
            "length": 0.6782611555843046,
            "org": 61,
            "speed": 80,
            "type": "LineString"
        },
        "205": {
            "dst": 61,
            "edits": "",
            "lanes": 3,
            "length": 0.6782611555843046,
            "org": 64,
            "speed": 80,
            "type": "LineString"
        },
        "206": {
            "dst": 60,
            "edits": "=Speed100",
            "lanes": 3,
            "length": 0.9234838522726707,
            "org": 68,
            "speed": 100,
            "type": "LineString"
        },
        "207": {
            "dst": 68,
            "edits": "=Speed100",
            "lanes": 3,
            "length": 0.9234838522726707,
            "org": 60,
            "speed": 100,
            "type": "LineString"
        },
        "208": {
            "dst": 59,
            "edits": "=Speed60 ,=4Lanes",
            "lanes": 4,
            "length": 0.8134338432681547,
            "org": 69,
            "speed": 60,
            "type": "LineString"
        },
        "209": {
            "dst": 69,
            "edits": "=Speed60 ,=4Lanes",
            "lanes": 4,
            "length": 0.8134338432681547,
            "org": 59,
            "speed": 60,
            "type": "LineString"
        },
        "210": {
            "dst": 65,
            "edits": "",
            "lanes": 3,
            "length": 0.5150340100259901,
            "org": 70,
            "speed": 80,
            "type": "LineString"
        },
        "211": {
            "dst": 70,
            "edits": "",
            "lanes": 3,
            "length": 0.5150340100259901,
            "org": 65,
            "speed": 80,
            "type": "LineString"
        },
        "212": {
            "dst": 64,
            "edits": "",
            "lanes": 3,
            "length": 0.6392410608621817,
            "org": 66,
            "speed": 80,
            "type": "LineString"
        },
        "213": {
            "dst": 66,
            "edits": "",
            "lanes": 3,
            "length": 0.6392410608621817,
            "org": 64,
            "speed": 80,
            "type": "LineString"
        },
        "214": {
            "dst": 65,
            "edits": "",
            "lanes": 3,
            "length": 0.6624315711686968,
            "org": 67,
            "speed": 80,
            "type": "LineString"
        },
        "215": {
            "dst": 67,
            "edits": "",
            "lanes": 3,
            "length": 0.6624315711686968,
            "org": 65,
            "speed": 80,
            "type": "LineString"
        },
        "216": {
            "dst": 71,
            "edits": "",
            "lanes": 3,
            "length": 0.8950731646265171,
            "org": 63,
            "speed": 80,
            "type": "LineString"
        },
        "217": {
            "dst": 63,
            "edits": "",
            "lanes": 3,
            "length": 0.8950731646265171,
            "org": 71,
            "speed": 80,
            "type": "LineString"
        },
        "218": {
            "dst": 61,
            "edits": "=4Lanes",
            "lanes": 4,
            "length": 0.8423940025923929,
            "org": 72,
            "speed": 80,
            "type": "LineString"
        },
        "219": {
            "dst": 72,
            "edits": "=4Lanes",
            "lanes": 4,
            "length": 0.8423940025923929,
            "org": 61,
            "speed": 80,
            "type": "LineString"
        },
        "220": {
            "dst": 66,
            "edits": "",
            "lanes": 3,
            "length": 0.824284296085535,
            "org": 68,
            "speed": 80,
            "type": "LineString"
        },
        "221": {
            "dst": 68,
            "edits": "",
            "lanes": 3,
            "length": 0.824284296085535,
            "org": 66,
            "speed": 80,
            "type": "LineString"
        },
        "222": {
            "dst": 73,
            "edits": "",
            "lanes": 3,
            "length": 0.6687616111593161,
            "org": 70,
            "speed": 80,
            "type": "LineString"
        },
        "223": {
            "dst": 70,
            "edits": "",
            "lanes": 3,
            "length": 0.6687616111593161,
            "org": 73,
            "speed": 80,
            "type": "LineString"
        },
        "224": {
            "dst": 67,
            "edits": "=Speed60 ,=Speed60",
            "lanes": 3,
            "length": 0.773518476994019,
            "org": 69,
            "speed": 60,
            "type": "LineString"
        },
        "225": {
            "dst": 69,
            "edits": "=Speed60 ,=Speed60",
            "lanes": 3,
            "length": 0.773518476994019,
            "org": 67,
            "speed": 60,
            "type": "LineString"
        },
        "226": {
            "dst": 74,
            "edits": "",
            "lanes": 3,
            "length": 0.8655863645120516,
            "org": 64,
            "speed": 80,
            "type": "LineString"
        },
        "227": {
            "dst": 64,
            "edits": "",
            "lanes": 3,
            "length": 0.8655863645120516,
            "org": 74,
            "speed": 80,
            "type": "LineString"
        },
        "228": {
            "dst": 65,
            "edits": "=4Lanes",
            "lanes": 4,
            "length": 0.6560767306708583,
            "org": 75,
            "speed": 80,
            "type": "LineString"
        },
        "229": {
            "dst": 75,
            "edits": "=4Lanes",
            "lanes": 4,
            "length": 0.6560767306708583,
            "org": 65,
            "speed": 80,
            "type": "LineString"
        },
        "230": {
            "dst": 57,
            "edits": "=4Lanes  ,-link231     ,-link195     ,-link184",
            "lanes": 4,
            "length": 2.618729826604969,
            "org": 76,
            "speed": 80,
            "type": "LineString"
        },
        "231": {
            "dst": 76,
            "edits": "-u-turn  ,=4Lanes",
            "lanes": 4,
            "length": 2.618729826604969,
            "org": 57,
            "speed": 80,
            "type": "LineString"
        },
        "232": {
            "dst": 68,
            "edits": "",
            "lanes": 3,
            "length": 0.4259274233608512,
            "org": 71,
            "speed": 80,
            "type": "LineString"
        },
        "233": {
            "dst": 71,
            "edits": "",
            "lanes": 3,
            "length": 0.4259274233608512,
            "org": 68,
            "speed": 80,
            "type": "LineString"
        },
        "234": {
            "dst": 69,
            "edits": "",
            "lanes": 3,
            "length": 0.6150902282076293,
            "org": 72,
            "speed": 80,
            "type": "LineString"
        },
        "235": {
            "dst": 72,
            "edits": "",
            "lanes": 3,
            "length": 0.6150902282076293,
            "org": 69,
            "speed": 80,
            "type": "LineString"
        },
        "236": {
            "dst": 77,
            "edits": "=Speed60",
            "lanes": 3,
            "length": 0.6403077250566278,
            "org": 67,
            "speed": 60,
            "type": "LineString"
        },
        "237": {
            "dst": 67,
            "edits": "=Speed60",
            "lanes": 3,
            "length": 0.6403077250566278,
            "org": 77,
            "speed": 60,
            "type": "LineString"
        },
        "238": {
            "dst": 66,
            "edits": "",
            "lanes": 3,
            "length": 0.9089361064550217,
            "org": 78,
            "speed": 80,
            "type": "LineString"
        },
        "239": {
            "dst": 78,
            "edits": "",
            "lanes": 3,
            "length": 0.9089361064550217,
            "org": 66,
            "speed": 80,
            "type": "LineString"
        },
        "240": {
            "dst": 68,
            "edits": "",
            "lanes": 3,
            "length": 0.5155840853040412,
            "org": 79,
            "speed": 80,
            "type": "LineString"
        },
        "241": {
            "dst": 79,
            "edits": "",
            "lanes": 3,
            "length": 0.5155840853040412,
            "org": 68,
            "speed": 80,
            "type": "LineString"
        },
        "242": {
            "dst": 73,
            "edits": "",
            "lanes": 3,
            "length": 0.5246755970795042,
            "org": 75,
            "speed": 80,
            "type": "LineString"
        },
        "243": {
            "dst": 75,
            "edits": "",
            "lanes": 3,
            "length": 0.5246755970795042,
            "org": 73,
            "speed": 80,
            "type": "LineString"
        },
        "244": {
            "dst": 72,
            "edits": "",
            "lanes": 3,
            "length": 0.6679671922396032,
            "org": 74,
            "speed": 80,
            "type": "LineString"
        },
        "245": {
            "dst": 74,
            "edits": "",
            "lanes": 3,
            "length": 0.6679671922396032,
            "org": 72,
            "speed": 80,
            "type": "LineString"
        },
        "246": {
            "dst": 75,
            "edits": "",
            "lanes": 3,
            "length": 0.7053708550190423,
            "org": 77,
            "speed": 80,
            "type": "LineString"
        },
        "247": {
            "dst": 77,
            "edits": "",
            "lanes": 3,
            "length": 0.7053708550190423,
            "org": 75,
            "speed": 80,
            "type": "LineString"
        },
        "248": {
            "dst": 80,
            "edits": "",
            "lanes": 3,
            "length": 0.3739847828569391,
            "org": 73,
            "speed": 80,
            "type": "LineString"
        },
        "249": {
            "dst": 73,
            "edits": "",
            "lanes": 3,
            "length": 0.3739847828569391,
            "org": 80,
            "speed": 80,
            "type": "LineString"
        },
        "250": {
            "dst": 71,
            "edits": "",
            "lanes": 3,
            "length": 0.5768391045999627,
            "org": 81,
            "speed": 80,
            "type": "LineString"
        },
        "251": {
            "dst": 81,
            "edits": "",
            "lanes": 3,
            "length": 0.5768391045999627,
            "org": 71,
            "speed": 80,
            "type": "LineString"
        },
        "252": {
            "dst": 74,
            "edits": "",
            "lanes": 3,
            "length": 0.661611999644313,
            "org": 78,
            "speed": 80,
            "type": "LineString"
        },
        "253": {
            "dst": 78,
            "edits": "",
            "lanes": 3,
            "length": 0.661611999644313,
            "org": 74,
            "speed": 80,
            "type": "LineString"
        },
        "254": {
            "dst": 69,
            "edits": "=Speed60",
            "lanes": 3,
            "length": 1.0192653636695952,
            "org": 82,
            "speed": 60,
            "type": "LineString"
        },
        "255": {
            "dst": 82,
            "edits": "=Speed60",
            "lanes": 3,
            "length": 1.0192653636695952,
            "org": 69,
            "speed": 60,
            "type": "LineString"
        },
        "256": {
            "dst": 83,
            "edits": "=4Lanes",
            "lanes": 4,
            "length": 0.37575220641718354,
            "org": 75,
            "speed": 80,
            "type": "LineString"
        },
        "257": {
            "dst": 75,
            "edits": "=4Lanes",
            "lanes": 4,
            "length": 0.37575220641718354,
            "org": 83,
            "speed": 80,
            "type": "LineString"
        },
        "258": {
            "dst": 81,
            "edits": "",
            "lanes": 3,
            "length": 0.7346860421887045,
            "org": 79,
            "speed": 80,
            "type": "LineString"
        },
        "259": {
            "dst": 79,
            "edits": "",
            "lanes": 3,
            "length": 0.7346860421887045,
            "org": 81,
            "speed": 80,
            "type": "LineString"
        },
        "260": {
            "dst": 84,
            "edits": "=Speed60",
            "lanes": 3,
            "length": 0.36765636618084413,
            "org": 77,
            "speed": 60,
            "type": "LineString"
        },
        "261": {
            "dst": 77,
            "edits": "=Speed60",
            "lanes": 3,
            "length": 0.36765636618084413,
            "org": 84,
            "speed": 60,
            "type": "LineString"
        },
        "262": {
            "dst": 83,
            "edits": "",
            "lanes": 3,
            "length": 0.5642696644586143,
            "org": 80,
            "speed": 80,
            "type": "LineString"
        },
        "263": {
            "dst": 80,
            "edits": "",
            "lanes": 3,
            "length": 0.5642696644586143,
            "org": 83,
            "speed": 80,
            "type": "LineString"
        },
        "264": {
            "dst": 72,
            "edits": "=4Lanes",
            "lanes": 4,
            "length": 0.9702512074891534,
            "org": 85,
            "speed": 80,
            "type": "LineString"
        },
        "265": {
            "dst": 85,
            "edits": "=4Lanes",
            "lanes": 4,
            "length": 0.9702512074891534,
            "org": 72,
            "speed": 80,
            "type": "LineString"
        },
        "266": {
            "dst": 79,
            "edits": "",
            "lanes": 3,
            "length": 0.4212358657952102,
            "org": 86,
            "speed": 80,
            "type": "LineString"
        },
        "267": {
            "dst": 86,
            "edits": "",
            "lanes": 3,
            "length": 0.4212358657952102,
            "org": 79,
            "speed": 80,
            "type": "LineString"
        },
        "268": {
            "dst": 78,
            "edits": "",
            "lanes": 3,
            "length": 0.8424455056461914,
            "org": 86,
            "speed": 80,
            "type": "LineString"
        },
        "269": {
            "dst": 86,
            "edits": "",
            "lanes": 3,
            "length": 0.8424455056461914,
            "org": 78,
            "speed": 80,
            "type": "LineString"
        },
        "270": {
            "dst": 84,
            "edits": "",
            "lanes": 3,
            "length": 0.670682720536038,
            "org": 83,
            "speed": 80,
            "type": "LineString"
        },
        "271": {
            "dst": 83,
            "edits": "",
            "lanes": 3,
            "length": 0.670682720536038,
            "org": 84,
            "speed": 80,
            "type": "LineString"
        },
        "272": {
            "dst": 87,
            "edits": "",
            "lanes": 3,
            "length": 0.33285872416463175,
            "org": 80,
            "speed": 80,
            "type": "LineString"
        },
        "273": {
            "dst": 80,
            "edits": "",
            "lanes": 3,
            "length": 0.33285872416463175,
            "org": 87,
            "speed": 80,
            "type": "LineString"
        },
        "274": {
            "dst": 83,
            "edits": "=4Lanes",
            "lanes": 4,
            "length": 0.3343722813325256,
            "org": 88,
            "speed": 80,
            "type": "LineString"
        },
        "275": {
            "dst": 88,
            "edits": "=4Lanes",
            "lanes": 4,
            "length": 0.3343722813325256,
            "org": 83,
            "speed": 80,
            "type": "LineString"
        },
        "276": {
            "dst": 82,
            "edits": "=Speed60 ,=Speed60",
            "lanes": 3,
            "length": 0.6101669299044559,
            "org": 84,
            "speed": 60,
            "type": "LineString"
        },
        "277": {
            "dst": 84,
            "edits": "=Speed60 ,=Speed60",
            "lanes": 3,
            "length": 0.6101669299044559,
            "org": 82,
            "speed": 60,
            "type": "LineString"
        },
        "278": {
            "dst": 89,
            "edits": "-u-turn",
            "lanes": 3,
            "length": 0.5308864880600539,
            "org": 87,
            "speed": 80,
            "type": "LineString"
        },
        "279": {
            "dst": 87,
            "edits": "",
            "lanes": 3,
            "length": 0.5308864880600539,
            "org": 89,
            "speed": 80,
            "type": "LineString"
        },
        "280": {
            "dst": 84,
            "edits": "=Speed60",
            "lanes": 3,
            "length": 0.32975037456952666,
            "org": 90,
            "speed": 60,
            "type": "LineString"
        },
        "281": {
            "dst": 90,
            "edits": "=Speed60",
            "lanes": 3,
            "length": 0.32975037456952666,
            "org": 84,
            "speed": 60,
            "type": "LineString"
        },
        "282": {
            "dst": 88,
            "edits": "",
            "lanes": 3,
            "length": 0.5531355828668536,
            "org": 87,
            "speed": 80,
            "type": "LineString"
        },
        "283": {
            "dst": 87,
            "edits": "",
            "lanes": 3,
            "length": 0.5531355828668536,
            "org": 88,
            "speed": 80,
            "type": "LineString"
        },
        "284": {
            "dst": 78,
            "edits": "",
            "lanes": 3,
            "length": 0.9781780645482371,
            "org": 91,
            "speed": 80,
            "type": "LineString"
        },
        "285": {
            "dst": 91,
            "edits": "",
            "lanes": 3,
            "length": 0.9781780645482371,
            "org": 78,
            "speed": 80,
            "type": "LineString"
        },
        "286": {
            "dst": 82,
            "edits": "=Speed60",
            "lanes": 3,
            "length": 0.7580826974611348,
            "org": 85,
            "speed": 60,
            "type": "LineString"
        },
        "287": {
            "dst": 85,
            "edits": "=Speed60",
            "lanes": 3,
            "length": 0.7580826974611348,
            "org": 82,
            "speed": 60,
            "type": "LineString"
        },
        "288": {
            "dst": 90,
            "edits": "",
            "lanes": 3,
            "length": 0.6645104807166131,
            "org": 88,
            "speed": 80,
            "type": "LineString"
        },
        "289": {
            "dst": 88,
            "edits": "",
            "lanes": 3,
            "length": 0.6645104807166131,
            "org": 90,
            "speed": 80,
            "type": "LineString"
        },
        "290": {
            "dst": 82,
            "edits": "=Speed60",
            "lanes": 3,
            "length": 0.3225402543291161,
            "org": 92,
            "speed": 60,
            "type": "LineString"
        },
        "291": {
            "dst": 92,
            "edits": "=Speed60",
            "lanes": 3,
            "length": 0.3225402543291161,
            "org": 82,
            "speed": 60,
            "type": "LineString"
        },
        "292": {
            "dst": 93,
            "edits": "",
            "lanes": 3,
            "length": 0.7785432698653865,
            "org": 89,
            "speed": 80,
            "type": "LineString"
        },
        "293": {
            "dst": 89,
            "edits": "-u-turn",
            "lanes": 3,
            "length": 0.7785432698653865,
            "org": 93,
            "speed": 80,
            "type": "LineString"
        },
        "294": {
            "dst": 85,
            "edits": "=Speed60",
            "lanes": 3,
            "length": 0.4429679172828973,
            "org": 94,
            "speed": 60,
            "type": "LineString"
        },
        "295": {
            "dst": 94,
            "edits": "=Speed60",
            "lanes": 3,
            "length": 0.4429679172828973,
            "org": 85,
            "speed": 60,
            "type": "LineString"
        },
        "296": {
            "dst": 95,
            "edits": "-u-turn  ,=4Lanes",
            "lanes": 4,
            "length": 0.2982465932247912,
            "org": 88,
            "speed": 80,
            "type": "LineString"
        },
        "297": {
            "dst": 88,
            "edits": "=4Lanes",
            "lanes": 4,
            "length": 0.2982465932247912,
            "org": 95,
            "speed": 80,
            "type": "LineString"
        },
        "298": {
            "dst": 90,
            "edits": "=Speed60",
            "lanes": 3,
            "length": 0.5692193326681281,
            "org": 92,
            "speed": 60,
            "type": "LineString"
        },
        "299": {
            "dst": 92,
            "edits": "=Speed60",
            "lanes": 3,
            "length": 0.5692193326681281,
            "org": 90,
            "speed": 60,
            "type": "LineString"
        },
        "300": {
            "dst": 96,
            "edits": "",
            "lanes": 3,
            "length": 0.5580349387327824,
            "org": 87,
            "speed": 80,
            "type": "LineString"
        },
        "301": {
            "dst": 87,
            "edits": "",
            "lanes": 3,
            "length": 0.5580349387327824,
            "org": 96,
            "speed": 80,
            "type": "LineString"
        },
        "302": {
            "dst": 97,
            "edits": "=4Lanes",
            "lanes": 4,
            "length": 0.377446412487175,
            "org": 85,
            "speed": 80,
            "type": "LineString"
        },
        "303": {
            "dst": 85,
            "edits": "=4Lanes",
            "lanes": 4,
            "length": 0.377446412487175,
            "org": 97,
            "speed": 80,
            "type": "LineString"
        },
        "304": {
            "dst": 98,
            "edits": "",
            "lanes": 3,
            "length": 0.9811961205136637,
            "org": 86,
            "speed": 80,
            "type": "LineString"
        },
        "305": {
            "dst": 86,
            "edits": "",
            "lanes": 3,
            "length": 0.9811961205136637,
            "org": 98,
            "speed": 80,
            "type": "LineString"
        },
        "306": {
            "dst": 99,
            "edits": "",
            "lanes": 3,
            "length": 0.8764591297582801,
            "org": 93,
            "speed": 80,
            "type": "LineString"
        },
        "307": {
            "dst": 93,
            "edits": "",
            "lanes": 3,
            "length": 0.8764591297582801,
            "org": 99,
            "speed": 80,
            "type": "LineString"
        },
        "308": {
            "dst": 91,
            "edits": "=Speed60",
            "lanes": 3,
            "length": 0.9206533189405088,
            "org": 94,
            "speed": 60,
            "type": "LineString"
        },
        "309": {
            "dst": 94,
            "edits": "=Speed60",
            "lanes": 3,
            "length": 0.9206533189405088,
            "org": 91,
            "speed": 60,
            "type": "LineString"
        },
        "310": {
            "dst": 97,
            "edits": "",
            "lanes": 3,
            "length": 0.8208927808669414,
            "org": 92,
            "speed": 80,
            "type": "LineString"
        },
        "311": {
            "dst": 92,
            "edits": "",
            "lanes": 3,
            "length": 0.8208927808669414,
            "org": 97,
            "speed": 80,
            "type": "LineString"
        },
        "312": {
            "dst": 96,
            "edits": "",
            "lanes": 3,
            "length": 0.6129807813701478,
            "org": 95,
            "speed": 80,
            "type": "LineString"
        },
        "313": {
            "dst": 95,
            "edits": "-u-turn  ,+link312",
            "lanes": 3,
            "length": 0.6129807813701478,
            "org": 96,
            "speed": 80,
            "type": "LineString"
        },
        "314": {
            "dst": 94,
            "edits": "",
            "lanes": 3,
            "length": 0.4271640502150796,
            "org": 100,
            "speed": 80,
            "type": "LineString"
        },
        "315": {
            "dst": 100,
            "edits": "",
            "lanes": 3,
            "length": 0.4271640502150796,
            "org": 94,
            "speed": 80,
            "type": "LineString"
        },
        "316": {
            "dst": 90,
            "edits": "",
            "lanes": 3,
            "length": 0.8304184522466393,
            "org": 101,
            "speed": 80,
            "type": "LineString"
        },
        "317": {
            "dst": 101,
            "edits": "-left    ,-u-turn  ,+link316",
            "lanes": 3,
            "length": 0.8304184522466393,
            "org": 90,
            "speed": 80,
            "type": "LineString"
        },
        "318": {
            "dst": 97,
            "edits": "",
            "lanes": 3,
            "length": 0.45325678649017936,
            "org": 100,
            "speed": 80,
            "type": "LineString"
        },
        "319": {
            "dst": 100,
            "edits": "",
            "lanes": 3,
            "length": 0.45325678649017936,
            "org": 97,
            "speed": 80,
            "type": "LineString"
        },
        "320": {
            "dst": 81,
            "edits": "",
            "lanes": 3,
            "length": 1.6725041488923809,
            "org": 102,
            "speed": 80,
            "type": "LineString"
        },
        "321": {
            "dst": 102,
            "edits": "",
            "lanes": 3,
            "length": 1.6725041488923809,
            "org": 81,
            "speed": 80,
            "type": "LineString"
        },
        "322": {
            "dst": 103,
            "edits": "",
            "lanes": 3,
            "length": 1.7772118454094548,
            "org": 76,
            "speed": 80,
            "type": "LineString"
        },
        "323": {
            "dst": 76,
            "edits": "-u-turn  ,-link335",
            "lanes": 3,
            "length": 1.7772118454094548,
            "org": 103,
            "speed": 80,
            "type": "LineString"
        },
        "324": {
            "dst": 103,
            "edits": "",
            "lanes": 3,
            "length": 0.5378912842464015,
            "org": 93,
            "speed": 80,
            "type": "LineString"
        },
        "325": {
            "dst": 93,
            "edits": "",
            "lanes": 3,
            "length": 0.5378912842464015,
            "org": 103,
            "speed": 80,
            "type": "LineString"
        },
        "326": {
            "dst": 91,
            "edits": "=Speed60",
            "lanes": 3,
            "length": 0.7693419840984158,
            "org": 98,
            "speed": 60,
            "type": "LineString"
        },
        "327": {
            "dst": 98,
            "edits": "=Speed60",
            "lanes": 3,
            "length": 0.7693419840984158,
            "org": 91,
            "speed": 60,
            "type": "LineString"
        },
        "328": {
            "dst": 95,
            "edits": "-u-turn  ,=4Lanes  ,-link312",
            "lanes": 4,
            "length": 0.8319473915976722,
            "org": 101,
            "speed": 80,
            "type": "LineString"
        },
        "329": {
            "dst": 101,
            "edits": "-left    ,-u-turn  ,=4Lanes",
            "lanes": 4,
            "length": 0.8319473915976722,
            "org": 95,
            "speed": 80,
            "type": "LineString"
        },
        "330": {
            "dst": 92,
            "edits": "=Speed60",
            "lanes": 3,
            "length": 0.8082194923876437,
            "org": 104,
            "speed": 60,
            "type": "LineString"
        },
        "331": {
            "dst": 104,
            "edits": "=Speed60",
            "lanes": 3,
            "length": 0.8082194923876437,
            "org": 92,
            "speed": 60,
            "type": "LineString"
        },
        "332": {
            "dst": 105,
            "edits": "",
            "lanes": 3,
            "length": 0.3310280444321762,
            "org": 91,
            "speed": 80,
            "type": "LineString"
        },
        "333": {
            "dst": 91,
            "edits": "",
            "lanes": 3,
            "length": 0.3310280444321762,
            "org": 105,
            "speed": 80,
            "type": "LineString"
        },
        "334": {
            "dst": 76,
            "edits": "-u-turn  ,=4Lanes  ,-link322",
            "lanes": 4,
            "length": 0.7958152196732181,
            "org": 106,
            "speed": 80,
            "type": "LineString"
        },
        "335": {
            "dst": 106,
            "edits": "-u-turn  ,=4Lanes",
            "lanes": 4,
            "length": 0.7958152196732181,
            "org": 76,
            "speed": 80,
            "type": "LineString"
        },
        "336": {
            "dst": 103,
            "edits": "",
            "lanes": 3,
            "length": 1.1589943309923805,
            "org": 96,
            "speed": 80,
            "type": "LineString"
        },
        "337": {
            "dst": 96,
            "edits": "",
            "lanes": 3,
            "length": 1.1589943309923805,
            "org": 103,
            "speed": 80,
            "type": "LineString"
        },
        "338": {
            "dst": 105,
            "edits": "",
            "lanes": 3,
            "length": 0.9365591665090799,
            "org": 100,
            "speed": 80,
            "type": "LineString"
        },
        "339": {
            "dst": 100,
            "edits": "",
            "lanes": 3,
            "length": 0.9365591665090799,
            "org": 105,
            "speed": 80,
            "type": "LineString"
        },
        "340": {
            "dst": 107,
            "edits": "",
            "lanes": 3,
            "length": 0.7654812104076297,
            "org": 97,
            "speed": 80,
            "type": "LineString"
        },
        "341": {
            "dst": 97,
            "edits": "",
            "lanes": 3,
            "length": 0.7654812104076297,
            "org": 107,
            "speed": 80,
            "type": "LineString"
        },
        "342": {
            "dst": 103,
            "edits": "",
            "lanes": 3,
            "length": 2.27542828964276,
            "org": 101,
            "speed": 80,
            "type": "LineString"
        },
        "343": {
            "dst": 101,
            "edits": "-left    ,-u-turn",
            "lanes": 3,
            "length": 2.27542828964276,
            "org": 103,
            "speed": 80,
            "type": "LineString"
        },
        "344": {
            "dst": 100,
            "edits": "",
            "lanes": 3,
            "length": 0.5803897220226986,
            "org": 108,
            "speed": 80,
            "type": "LineString"
        },
        "345": {
            "dst": 108,
            "edits": "-left_T",
            "lanes": 3,
            "length": 0.5803897220226986,
            "org": 100,
            "speed": 80,
            "type": "LineString"
        },
        "346": {
            "dst": 109,
            "edits": "",
            "lanes": 3,
            "length": 0.23035036220006838,
            "org": 105,
            "speed": 80,
            "type": "LineString"
        },
        "347": {
            "dst": 105,
            "edits": "",
            "lanes": 3,
            "length": 0.23035036220006838,
            "org": 109,
            "speed": 80,
            "type": "LineString"
        },
        "348": {
            "dst": 98,
            "edits": "=Speed60",
            "lanes": 3,
            "length": 0.4406572877513932,
            "org": 110,
            "speed": 60,
            "type": "LineString"
        },
        "349": {
            "dst": 110,
            "edits": "=Speed60",
            "lanes": 3,
            "length": 0.4406572877513932,
            "org": 98,
            "speed": 60,
            "type": "LineString"
        },
        "350": {
            "dst": 104,
            "edits": "=4Lanes",
            "lanes": 4,
            "length": 0.5672042436869829,
            "org": 101,
            "speed": 80,
            "type": "LineString"
        },
        "351": {
            "dst": 101,
            "edits": "-u-turn  ,=4Lanes",
            "lanes": 4,
            "length": 0.5672042436869829,
            "org": 104,
            "speed": 80,
            "type": "LineString"
        },
        "352": {
            "dst": 106,
            "edits": "-u-turn  ,=4Lanes",
            "lanes": 4,
            "length": 0.5682333129419728,
            "org": 104,
            "speed": 80,
            "type": "LineString"
        },
        "353": {
            "dst": 104,
            "edits": "=4Lanes",
            "lanes": 4,
            "length": 0.5682333129419728,
            "org": 106,
            "speed": 80,
            "type": "LineString"
        },
        "354": {
            "dst": 102,
            "edits": "",
            "lanes": 3,
            "length": 1.7542451699560802,
            "org": 98,
            "speed": 80,
            "type": "LineString"
        },
        "355": {
            "dst": 98,
            "edits": "",
            "lanes": 3,
            "length": 1.7542451699560802,
            "org": 102,
            "speed": 80,
            "type": "LineString"
        },
        "356": {
            "dst": 109,
            "edits": "=4Lanes",
            "lanes": 4,
            "length": 0.7488041355627612,
            "org": 110,
            "speed": 80,
            "type": "LineString"
        },
        "357": {
            "dst": 110,
            "edits": "=4Lanes",
            "lanes": 4,
            "length": 0.7488041355627612,
            "org": 109,
            "speed": 80,
            "type": "LineString"
        },
        "358": {
            "dst": 108,
            "edits": "-left_T  ,=4Lanes",
            "lanes": 4,
            "length": 1.0540072130865947,
            "org": 109,
            "speed": 80,
            "type": "LineString"
        },
        "359": {
            "dst": 109,
            "edits": "=4Lanes",
            "lanes": 4,
            "length": 1.0540072130865947,
            "org": 108,
            "speed": 80,
            "type": "LineString"
        },
        "360": {
            "dst": 104,
            "edits": "=4Lanes",
            "lanes": 4,
            "length": 0.8044787578674181,
            "org": 107,
            "speed": 80,
            "type": "LineString"
        },
        "361": {
            "dst": 107,
            "edits": "=4Lanes",
            "lanes": 4,
            "length": 0.8044787578674181,
            "org": 104,
            "speed": 80,
            "type": "LineString"
        },
        "362": {
            "dst": 108,
            "edits": "-left_T  ,=4Lanes",
            "lanes": 4,
            "length": 0.516553782828301,
            "org": 107,
            "speed": 80,
            "type": "LineString"
        },
        "363": {
            "dst": 107,
            "edits": "=4Lanes",
            "lanes": 4,
            "length": 0.516553782828301,
            "org": 108,
            "speed": 80,
            "type": "LineString"
        },
        "364": {
            "dst": 111,
            "edits": "",
            "lanes": 3,
            "length": 2.3563225568518327,
            "org": 110,
            "speed": 80,
            "type": "LineString"
        },
        "365": {
            "dst": 110,
            "edits": "",
            "lanes": 3,
            "length": 2.3563225568518327,
            "org": 111,
            "speed": 80,
            "type": "LineString"
        },
        "366": {
            "dst": 102,
            "edits": "",
            "lanes": 3,
            "length": 0.989944388143513,
            "org": 111,
            "speed": 80,
            "type": "LineString"
        },
        "367": {
            "dst": 111,
            "edits": "",
            "lanes": 3,
            "length": 0.989944388143513,
            "org": 102,
            "speed": 80,
            "type": "LineString"
        }
    },
    "nodes": {
        "0": {
            "lat": 24.405820263441573,
            "lon": 54.47737475340553
        },
        "1": {
            "lat": 24.402754094244056,
            "lon": 54.4883370839816
        },
        "2": {
            "lat": 24.407745494422247,
            "lon": 54.471032262143666
        },
        "3": {
            "lat": 24.419296263787047,
            "lon": 54.47737475340553
        },
        "4": {
            "lat": 24.412023680389083,
            "lon": 54.47259830936881
        },
        "5": {
            "lat": 24.416800816709703,
            "lon": 54.47095395978241
        },
        "6": {
            "lat": 24.410027211645712,
            "lon": 54.46281051421162
        },
        "7": {
            "lat": 24.420437023159025,
            "lon": 54.48739745564651
        },
        "8": {
            "lat": 24.41701471410691,
            "lon": 54.46515958504935
        },
        "9": {
            "lat": 24.42606937138801,
            "lon": 54.47416435659397
        },
        "10": {
            "lat": 24.423574058256865,
            "lon": 54.48857199106537
        },
        "11": {
            "lat": 24.424144419895143,
            "lon": 54.45364913794447
        },
        "12": {
            "lat": 24.41537482479761,
            "lon": 54.44323492389721
        },
        "13": {
            "lat": 24.439614495655867,
            "lon": 54.45545009225339
        },
        "14": {
            "lat": 24.426211959219085,
            "lon": 54.44495757584487
        },
        "15": {
            "lat": 24.420864805264834,
            "lon": 54.44401794750978
        },
        "16": {
            "lat": 24.427210069524044,
            "lon": 54.437440549164144
        },
        "17": {
            "lat": 24.432770825221304,
            "lon": 54.438380177499226
        },
        "18": {
            "lat": 24.41979534728119,
            "lon": 54.427496149284416
        },
        "19": {
            "lat": 24.423003694040208,
            "lon": 54.42773105636818
        },
        "20": {
            "lat": 24.444105452506207,
            "lon": 54.440337736530665
        },
        "21": {
            "lat": 24.428422049991756,
            "lon": 54.42906219650958
        },
        "22": {
            "lat": 24.433982752256753,
            "lon": 54.43000182484466
        },
        "23": {
            "lat": 24.422718510965005,
            "lon": 54.416925330514644
        },
        "24": {
            "lat": 24.444675721292903,
            "lon": 54.43172447679233
        },
        "25": {
            "lat": 24.430346936212047,
            "lon": 54.41958761079741
        },
        "26": {
            "lat": 24.43562239970781,
            "lon": 54.421466867467586
        },
        "27": {
            "lat": 24.444461870800236,
            "lon": 54.419431006074895
        },
        "28": {
            "lat": 24.432699535033002,
            "lon": 54.413793236064336
        },
        "29": {
            "lat": 24.424572189431757,
            "lon": 54.40987811800145
        },
        "30": {
            "lat": 24.437689750888683,
            "lon": 54.41622060926333
        },
        "31": {
            "lat": 24.43626399508087,
            "lon": 54.4046318597972
        },
        "32": {
            "lat": 24.441467925808368,
            "lon": 54.40698093063493
        },
        "33": {
            "lat": 24.427138776192717,
            "lon": 54.40040353228928
        },
        "34": {
            "lat": 24.44788343514337,
            "lon": 54.410113025085224
        },
        "35": {
            "lat": 24.44339261289474,
            "lon": 54.40416204562965
        },
        "36": {
            "lat": 24.439757068173446,
            "lon": 54.39954220631545
        },
        "37": {
            "lat": 24.445744968313914,
            "lon": 54.401969579514436
        },
        "38": {
            "lat": 24.455581615269704,
            "lon": 54.403222417294565
        },
        "39": {
            "lat": 24.442038206527165,
            "lon": 54.3974280425615
        },
        "40": {
            "lat": 24.43191534030198,
            "lon": 54.38396003642518
        },
        "41": {
            "lat": 24.45073466780502,
            "lon": 54.396958228393956
        },
        "42": {
            "lat": 24.447028052765692,
            "lon": 54.392494993802266
        },
        "43": {
            "lat": 24.443178760225216,
            "lon": 54.38748364268178
        },
        "44": {
            "lat": 24.436834299338585,
            "lon": 54.37965340655601
        },
        "45": {
            "lat": 24.434267909866616,
            "lon": 54.37675621918948
        },
        "46": {
            "lat": 24.46149748961335,
            "lon": 54.38677892143046
        },
        "47": {
            "lat": 24.473684740288864,
            "lon": 54.39139876074465
        },
        "48": {
            "lat": 24.457933743160417,
            "lon": 54.382393989200025
        },
        "49": {
            "lat": 24.4538709492202,
            "lon": 54.37730433571829
        },
        "50": {
            "lat": 24.43191534030198,
            "lon": 54.37354582237792
        },
        "51": {
            "lat": 24.44510342118977,
            "lon": 54.366342005142215
        },
        "52": {
            "lat": 24.466842920224757,
            "lon": 54.38192417503248
        },
        "53": {
            "lat": 24.450164426433535,
            "lon": 54.37244958932031
        },
        "54": {
            "lat": 24.442537200039855,
            "lon": 54.363209910691914
        },
        "55": {
            "lat": 24.463208052095037,
            "lon": 54.377382638079546
        },
        "56": {
            "lat": 24.45914542826737,
            "lon": 54.37252789168157
        },
        "57": {
            "lat": 24.48052618849911,
            "lon": 54.38654401434668
        },
        "58": {
            "lat": 24.455510337981387,
            "lon": 54.36759484292234
        },
        "59": {
            "lat": 24.47382727425297,
            "lon": 54.37534677668685
        },
        "60": {
            "lat": 24.45023570674609,
            "lon": 54.36133065402173
        },
        "61": {
            "lat": 24.470121338734952,
            "lon": 54.37064863501138
        },
        "62": {
            "lat": 24.478174482624144,
            "lon": 54.381297756142416
        },
        "63": {
            "lat": 24.447740871816908,
            "lon": 54.35819855957143
        },
        "64": {
            "lat": 24.4659163951749,
            "lon": 54.3657938886134
        },
        "65": {
            "lat": 24.487082227359895,
            "lon": 54.38121945378116
        },
        "66": {
            "lat": 24.46171131119411,
            "lon": 54.36148725874424
        },
        "67": {
            "lat": 24.483519205140713,
            "lon": 54.375973195576904
        },
        "68": {
            "lat": 24.456650769755214,
            "lon": 54.35553627928866
        },
        "69": {
            "lat": 24.47924344528805,
            "lon": 54.36994391376007
        },
        "70": {
            "lat": 24.489861314637682,
            "lon": 54.38529117656657
        },
        "71": {
            "lat": 24.453942227436002,
            "lon": 54.352560789560876
        },
        "72": {
            "lat": 24.475822732803447,
            "lon": 54.365167469723346
        },
        "73": {
            "lat": 24.49470675584789,
            "lon": 54.38137605850368
        },
        "74": {
            "lat": 24.471831784068947,
            "lon": 54.36023442096411
        },
        "75": {
            "lat": 24.491785262169625,
            "lon": 54.37730433571829
        },
        "76": {
            "lat": 24.498968185509376,
            "lon": 54.370449094665354
        },
        "77": {
            "lat": 24.487866078705995,
            "lon": 54.37182317043026
        },
        "78": {
            "lat": 24.467769438457097,
            "lon": 54.355457976927404
        },
        "79": {
            "lat": 24.459929453596235,
            "lon": 54.351934370670826
        },
        "80": {
            "lat": 24.497414421094035,
            "lon": 54.37918359238848
        },
        "81": {
            "lat": 24.455082673404643,
            "lon": 54.34700132191159
        },
        "82": {
            "lat": 24.487153486775007,
            "lon": 54.36485426027832
        },
        "83": {
            "lat": 24.494279224426837,
            "lon": 54.37479866015805
        },
        "84": {
            "lat": 24.490502633751603,
            "lon": 54.36963070431504
        },
        "85": {
            "lat": 24.482664064793486,
            "lon": 54.35921649026777
        },
        "86": {
            "lat": 24.46278041365272,
            "lon": 54.34919378802679
        },
        "87": {
            "lat": 24.499765767294825,
            "lon": 54.37714773099577
        },
        "88": {
            "lat": 24.496701883260897,
            "lon": 54.3728411011266
        },
        "89": {
            "lat": 24.50268707555913,
            "lon": 54.38129775614243
        },
        "90": {
            "lat": 24.492925365338095,
            "lon": 54.367751447644864
        },
        "91": {
            "lat": 24.474468675094116,
            "lon": 54.34919378802679
        },
        "92": {
            "lat": 24.489718798834993,
            "lon": 54.363366515414434
        },
        "93": {
            "lat": 24.509526946405327,
            "lon": 54.38294210572884
        },
        "94": {
            "lat": 24.479956082019555,
            "lon": 54.35600609345621
        },
        "95": {
            "lat": 24.49876823185281,
            "lon": 54.370961844456424
        },
        "96": {
            "lat": 24.50368457990662,
            "lon": 54.37370242710044
        },
        "97": {
            "lat": 24.48530072886374,
            "lon": 54.356867419430046
        },
        "98": {
            "lat": 24.46990753143423,
            "lon": 54.343477715654984
        },
        "99": {
            "lat": 24.514656605249392,
            "lon": 54.389519504074485
        },
        "100": {
            "lat": 24.48287785042515,
            "lon": 54.35326551081219
        },
        "101": {
            "lat": 24.498839484646858,
            "lon": 54.36274009652437
        },
        "102": {
            "lat": 24.458931602330725,
            "lon": 54.331027640215034
        },
        "103": {
            "lat": 24.51287549743904,
            "lon": 54.379105290027226
        },
        "104": {
            "lat": 24.495490559678117,
            "lon": 54.35851176901646
        },
        "105": {
            "lat": 24.476677919640867,
            "lon": 54.347001321911584
        },
        "106": {
            "lat": 24.499009292888832,
            "lon": 54.36258418562757
        },
        "107": {
            "lat": 24.4908589207353,
            "lon": 54.352404184838356
        },
        "108": {
            "lat": 24.48693970840858,
            "lon": 54.34966360219433
        },
        "109": {
            "lat": 24.478245747084227,
            "lon": 54.34551357704769
        },
        "110": {
            "lat": 24.47304333545319,
            "lon": 54.34081543537223
        },
        "111": {
            "lat": 24.461141119505438,
            "lon": 54.321553054502864
        }
    }
}